detecta_shared/abstractions/__init__.py
detecta_shared/abstractions/integration_events.py
detecta_shared/abstractions/message_bus.py
detecta_shared/rabbitmq/__init__.py
detecta_shared/rabbitmq/rabbitmq_connection.py
detecta_shared/rabbitmq/rabbitmq_event_listener.py
detecta_shared/rabbitmq/rabbitmq_message_bus.py
detecta_shared/rabbitmq/rabbitmq_params.py
detecta_shared/rabbitmq/rabbitmq_publisher.py
detecta_shared/rabbitmq/subscription_manager.py
detecta_shared-0.1.0.dist-info/METADATA
detecta_shared-0.1.0.dist-info/WHEEL
detecta_shared-0.1.0.dist-info/top_level.txt
detecta_shared-0.1.0.dist-info/RECORD
